rxnSMILES4AtomEco/__init__.py
rxnSMILES4AtomEco/atom_eco.py
rxnSMILES4AtomEco/test.py
rxnsmiles4atomeco-2025.6.1.dist-info/METADATA
rxnsmiles4atomeco-2025.6.1.dist-info/WHEEL
rxnsmiles4atomeco-2025.6.1.dist-info/top_level.txt
rxnsmiles4atomeco-2025.6.1.dist-info/RECORD
